deepwave-0.0.26.dist-info/RECORD
deepwave-0.0.26.dist-info/WHEEL
deepwave-0.0.26.dist-info/METADATA
deepwave-0.0.26.dist-info/licenses/LICENSE
deepwave/scalar.cu
deepwave/acoustic.cu
deepwave/_version.py
deepwave/libdeepwave_C.dylib
deepwave/regular_grid.py
deepwave/storage_utils.c
deepwave/backend_utils.py
deepwave/scalar.py
deepwave/simple_compress.h
deepwave/acoustic.c
deepwave/elastic.c
deepwave/__init__.py
deepwave/acoustic.py
deepwave/wavelets.py
deepwave/location_interpolation.py
deepwave/common.py
deepwave/storage_utils.cu
deepwave/scalar_born.c
deepwave/elastic.py
deepwave/scalar_born.cu
deepwave/staggered_grid.py
deepwave/staggered_grid.h
deepwave/simple_compress.c
deepwave/common_cpu.h
deepwave/storage_utils.h
deepwave/regular_grid.h
deepwave/simple_compress.cu
deepwave/scalar.c
deepwave/common_gpu.h
deepwave/scalar_born.py
deepwave/elastic.cu
