Metadata-Version: 2.4
Name: deepwave
Version: 0.0.26
Summary: Wave propagation modules for PyTorch
Author-Email: Alan Richardson <alan@ausargeo.com>
License-Expression: MIT
License-File: LICENSE
Classifier: Programming Language :: Python :: 3
Project-URL: Homepage, https://github.com/ar4/deepwave
Project-URL: Bug Tracker, https://github.com/ar4/deepwave/issues
Requires-Python: >=3.8
Requires-Dist: torch
Requires-Dist: setuptools
